setup.py
vmock/__init__.py
vmock/matchers.py
vmock/methodmock.py
vmock/mock_src_gen.py
vmock/mockcallaction.py
vmock/mockcontrol.py
vmock/mockerrors.py
vmock/vmock_defs.py
vmock.egg-info/PKG-INFO
vmock.egg-info/SOURCES.txt
vmock.egg-info/dependency_links.txt
vmock.egg-info/requires.txt
vmock.egg-info/top_level.txt
vmock/helpers/__init__.py
vmock/helpers/dbmock.py