Metadata-Version: 1.1
Name: vmock
Version: 0.1
Summary: Advanced Mock library following record and replay approach.
Home-page: https://github.com/vburenin/vmock
Author: Volodymyr Burenin
Author-email: vburenin@gmail.com
License: License :: MIT
Platform: UNKNOWN
Classifier: License :: OSI Approved :: MIT License
Classifier: Development Status :: 5 - Production/Stable
Classifier: Intended Audience :: Developers
Classifier: Programming Language :: Python :: 3.2
Classifier: Programming Language :: Python :: 3.3
Classifier: Programming Language :: Python :: 3.4
Classifier: Topic :: Software Development :: Quality Assurance
